bladerfsdraio/__init__.py
bladerfsdraio/bladerfsdraio.py
bladerf_sdr_aio-0.9.dist-info/LICENSE
bladerf_sdr_aio-0.9.dist-info/METADATA
bladerf_sdr_aio-0.9.dist-info/WHEEL
bladerf_sdr_aio-0.9.dist-info/top_level.txt
bladerf_sdr_aio-0.9.dist-info/RECORD
