Metadata-Version: 2.1
Name: bladerf-sdr-aio
Version: 0.9
Summary: An asynchronous Python wrapper based on the official bladerf python library from Nuand
Home-page: https://github.com/pyrtlsdr/pyrtlsdr
Author: Christoph Schmied
Author-email: Christoph Schmied <smith1401@hotmail.com>
License: MIT
Project-URL: Homepage, https://github.com/smith1401/bladerf-sdr-aio
Project-URL: Bug Tracker, https://github.com/smith1401/bladerf-sdr-aio/issues
Keywords: bladerf sdr cffi radio libbladerf asyncio
Platform: any
Classifier: Programming Language :: Python :: 3
Classifier: License :: OSI Approved :: MIT License
Classifier: Operating System :: OS Independent
Requires-Python: >=3
License-File: LICENSE
Requires-Dist: cffi
Requires-Dist: bladerf
Requires-Dist: humanize
Requires-Dist: numpy
